datax/__init__.py
DataX_dtd-0.0.1.dist-info/METADATA
DataX_dtd-0.0.1.dist-info/WHEEL
DataX_dtd-0.0.1.dist-info/top_level.txt
DataX_dtd-0.0.1.dist-info/RECORD
