Metadata-Version: 2.1
Name: DataX-dtd
Version: 0.0.1
Summary: Awesome and easy to use database
Home-page: https://github.com/AwesomeAnimations/dataxbugs
Author: AwesomeAnimations
Author-email: None@sorry.com
License: UNKNOWN
Project-URL: Bug Tracker, https://github.com/AwesomeAnimations/dataxbugs
Platform: UNKNOWN
Classifier: Programming Language :: Python :: 3
Classifier: License :: OSI Approved
Classifier: Operating System :: OS Independent
Requires-Python: >=3.6
